{
  "description": "Secure storage for recovered temporal artifacts and related research data. Access strictly limited. Contains items with potential for severe temporal disruption.",
  "themes": [
    "Temporal Artifacts",
    "Time Travel",
    "Chronal Anomalies",
    "Paradox Prevention"
  ],
  "securityLevel": "Code Black",
  "containmentProcedures": [
    "Temporal Stasis Fields",
    "Chroniton Shielding",
    "Anti-Paradox Protocols",
    "Reality Anchors"
  ],
  "relatedFiles": [
    "Chronos_Vault_Inventory.md",
    "Project_Chronos_Report.pdf",
    "Temporal_Anomaly_Case_Studies.docx"
  ],
  "researchContext": "Study of the effects of temporal manipulation and the potential dangers of altering the timeline. Development of safeguards against temporal paradoxes. Research focuses on understanding the nature of time, causality, and the multiverse. Includes analysis of retrieved temporal artifacts and documentation of related experiments.",
  "anomalies": [
    "Temporal Displacements",
    "Paradoxical Events",
    "Causality Violations",
    "Timeline Fluctuations"
  ],
  "timestamp": "2024-07-29T12:00:00Z"
}